SARLens/__init__.py
SARLens/autofocus/compressor.py
SARLens/autofocus/constants.py
SARLens/autofocus/metrics.py
SARLens/processor/__init__.py
SARLens/processor/decode.py
SARLens/processor/focus.py
SARLens/processor/rda_simple.py
SARLens/utils/__init__.py
SARLens/utils/io.py
SARLens/utils/printsummary.py
sentinel1decoder/__init__.py
sentinel1decoder/_fdbaq_decoder.py
sentinel1decoder/_headers.py
sentinel1decoder/_lookup_tables.py
sentinel1decoder/_sample_code.py
sentinel1decoder/_sample_code_bypass.py
sentinel1decoder/_sample_value_reconstruction.py
sentinel1decoder/_user_data_decoder.py
sentinel1decoder/constants.py
sentinel1decoder/l0decoder.py
sentinel1decoder/l0file.py
sentinel1decoder/utilities.py
SARLens-0.2.dist-info/METADATA
SARLens-0.2.dist-info/WHEEL
SARLens-0.2.dist-info/top_level.txt
SARLens-0.2.dist-info/RECORD
